zenithdb/__init__.py
zenithdb/aggregations.py
zenithdb/operations.py
zenithdb/query.py
zenithdb/core/__init__.py
zenithdb/core/collection.py
zenithdb/core/connection_pool.py
zenithdb/core/database.py
zenithdb/migrations/__init__.py
zenithdb/migrations/manager.py
zenithdb/utils/__init__.py
zenithdb-2.0.0.dist-info/LICENSE
zenithdb-2.0.0.dist-info/METADATA
zenithdb-2.0.0.dist-info/WHEEL
zenithdb-2.0.0.dist-info/top_level.txt
zenithdb-2.0.0.dist-info/RECORD
