Metadata-Version: 2.2
Name: zenithdb
Version: 2.0.0
Summary: SQLite-powered document database with MongoDB-like syntax, full-text search, and advanced querying capabilities
Home-page: https://github.com/jolovicdev/zenithdb
Author: jolovicdev
Author-email: jolovic@pm.me
Project-URL: Bug Reports, https://github.com/jolovicdev/zenithdb/issues
Project-URL: Source, https://github.com/jolovicdev/zenithdb
Project-URL: Documentation, https://github.com/jolovicdev/zenithdb/blob/master/README.md
Keywords: database,nosql,document-store,sqlite,json,document-database,mongodb-alternative,embedded-database,document-oriented,nosql-database,sqlite-wrapper
Classifier: Development Status :: 4 - Beta
Classifier: Intended Audience :: Developers
Classifier: License :: OSI Approved :: MIT License
Classifier: Operating System :: OS Independent
Classifier: Programming Language :: Python :: 3 :: Only
Classifier: Programming Language :: Python :: 3.7
Classifier: Programming Language :: Python :: 3.8
Classifier: Programming Language :: Python :: 3.9
Classifier: Programming Language :: Python :: 3.10
Classifier: Programming Language :: Python :: 3.11
Classifier: Programming Language :: Python :: 3.12
Classifier: Topic :: Database
Classifier: Topic :: Database :: Database Engines/Servers
Classifier: Topic :: Software Development :: Libraries :: Python Modules
Requires-Python: >=3.7
License-File: LICENSE
Provides-Extra: dev
Requires-Dist: pytest<8.0.0,>=7.0.0; extra == "dev"
Requires-Dist: pytest-cov<5.0.0,>=4.0.0; extra == "dev"
Requires-Dist: black<23.0.0,>=22.0.0; extra == "dev"
Requires-Dist: isort<6.0.0,>=5.0.0; extra == "dev"
Provides-Extra: docs
Requires-Dist: sphinx<5.0.0,>=4.0.0; extra == "docs"
Requires-Dist: sphinx-rtd-theme<2.0.0,>=1.0.0; extra == "docs"
Dynamic: author
Dynamic: author-email
Dynamic: classifier
Dynamic: description
Dynamic: description-content-type
Dynamic: home-page
Dynamic: keywords
Dynamic: project-url
Dynamic: provides-extra
Dynamic: requires-python
Dynamic: summary
